odoo/addons/delivery_correos_express/README.rst
odoo/addons/delivery_correos_express/__init__.py
odoo/addons/delivery_correos_express/__manifest__.py
odoo/addons/delivery_correos_express/doc/GrabacionEnvios/DC_SP_ apiRestSeguimientoEnviosk8s_v01.03.pdf
odoo/addons/delivery_correos_express/doc/GrabacionEnvios/DC_SP_WS_GrabacionEnviosRest_v03.12.pdf
odoo/addons/delivery_correos_express/doc/GrabacionEnvios/DC_SP_WS_ListEnviosRest_v01.01.pdf
odoo/addons/delivery_correos_express/doc/GrabacionEnvios/DC_SP_WS_apiRestEtiquetaTransporte_v01.01.pdf
odoo/addons/delivery_correos_express/doc/GrabacionRecogidas/DC_SP_Seguimiento_Recogidak8s_v01.00.pdf
odoo/addons/delivery_correos_express/doc/GrabacionRecogidas/DC_SP_WS_GrabacionRecogidaRest_v1.08.pdf
odoo/addons/delivery_correos_express/i18n/delivery_correos_express.pot
odoo/addons/delivery_correos_express/i18n/es.po
odoo/addons/delivery_correos_express/i18n/it.po
odoo/addons/delivery_correos_express/models/__init__.py
odoo/addons/delivery_correos_express/models/correos_express_request.py
odoo/addons/delivery_correos_express/models/delivery_carrier.py
odoo/addons/delivery_correos_express/models/stock_picking.py
odoo/addons/delivery_correos_express/readme/CONFIGURE.md
odoo/addons/delivery_correos_express/readme/CONTRIBUTORS.md
odoo/addons/delivery_correos_express/readme/DESCRIPTION.md
odoo/addons/delivery_correos_express/readme/INSTALL.md
odoo/addons/delivery_correos_express/readme/ROADMAP.md
odoo/addons/delivery_correos_express/readme/USAGE.md
odoo/addons/delivery_correos_express/static/description/icon.png
odoo/addons/delivery_correos_express/static/description/index.html
odoo/addons/delivery_correos_express/tests/__init__.py
odoo/addons/delivery_correos_express/tests/test_correos_express_request.py
odoo/addons/delivery_correos_express/tests/test_delivery_correos_express.py
odoo/addons/delivery_correos_express/views/delivery_carrier_view.xml
odoo/addons/delivery_correos_express/views/stock_picking_views.xml
odoo_addon_delivery_correos_express-18.0.1.0.0.2.dist-info/METADATA
odoo_addon_delivery_correos_express-18.0.1.0.0.2.dist-info/WHEEL
odoo_addon_delivery_correos_express-18.0.1.0.0.2.dist-info/top_level.txt
odoo_addon_delivery_correos_express-18.0.1.0.0.2.dist-info/RECORD
