Metadata-Version: 2.1
Name: odoo-addon-delivery_correos_express
Version: 18.0.1.0.0.2
Requires-Python: >=3.10
Requires-Dist: odoo-addon-delivery_package_number==18.0.*
Requires-Dist: odoo-addon-delivery_state==18.0.*
Requires-Dist: odoo==18.0.*
Requires-Dist: unidecode
Summary: Delivery Carrier implementation for Correos Express using their API
Home-page: https://github.com/OCA/delivery-carrier
License: AGPL-3
Author: Studio73, Odoo Community Association (OCA)
Author-email: support@odoo-community.org
Classifier: Programming Language :: Python
Classifier: Framework :: Odoo
Classifier: Framework :: Odoo :: 18.0
Classifier: License :: OSI Approved :: GNU Affero General Public License v3
